LICENSE
echo1_geopix/__init__.py
echo1_geopix/echo1_geopix.py
echo1_geopix-1.0.2.dist-info/LICENSE
echo1_geopix-1.0.2.dist-info/WHEEL
echo1_geopix-1.0.2.dist-info/METADATA
echo1_geopix-1.0.2.dist-info/RECORD
